hgfluiddyn/__init__.py
hgfluiddyn/_version.py
hg_fluiddyn-0.0.5.dist-info/LICENSE.txt
hg_fluiddyn-0.0.5.dist-info/METADATA
hg_fluiddyn-0.0.5.dist-info/WHEEL
hg_fluiddyn-0.0.5.dist-info/top_level.txt
hg_fluiddyn-0.0.5.dist-info/RECORD
